historify/__init__.py
historify/changelog.py
historify/cli.py
historify/cli_category.py
historify/cli_comment.py
historify/cli_config.py
historify/cli_duplicates.py
historify/cli_init.py
historify/cli_lifecycle.py
historify/cli_log.py
historify/cli_scan.py
historify/cli_snapshot.py
historify/cli_status.py
historify/cli_verify.py
historify/config.py
historify/csv_manager.py
historify/hash.py
historify/key_manager.py
historify/media_packer.py
historify/minisign.py
historify/repository.py
historify-0.3.2.dist-info/LICENSE
historify-0.3.2.dist-info/METADATA
historify-0.3.2.dist-info/WHEEL
historify-0.3.2.dist-info/entry_points.txt
historify-0.3.2.dist-info/RECORD
