Metadata-Version: 2.3
Name: historify
Version: 0.3.2
Summary: A tool for revision-safe logging of file changes
License: MIT
Keywords: versioning,changelog,integrity,cryptography
Author: Kevin Bortis
Author-email: kevin@bortis.ch
Requires-Python: >=3.12
Classifier: Development Status :: 4 - Beta
Classifier: Intended Audience :: System Administrators
Classifier: License :: OSI Approved :: MIT License
Classifier: Programming Language :: Python :: 3
Classifier: Programming Language :: Python :: 3.12
Classifier: Topic :: System :: Archiving
Classifier: Topic :: System :: Logging
Requires-Dist: blake3 (>=0.3.4)
Requires-Dist: click (>=8.1.7)
Requires-Dist: configparser (>=7.1.0)
Requires-Dist: pexpect (>=4.9.0)
Requires-Dist: pycdlib (>=1.14.0)
